README.md
blackout.py
setup.py
blackout.egg-info/PKG-INFO
blackout.egg-info/SOURCES.txt
blackout.egg-info/dependency_links.txt
blackout.egg-info/entry_points.txt
blackout.egg-info/top_level.txt