Metadata-Version: 2.1
Name: blackout
Version: 1.0.4
Summary: A python package making it easy to drop a multi-module package from sys.modules
Home-page: https://github.com/mikemalinowski/blackout
Author: Mike Malinowski
Author-email: mike@twisted.space
License: UNKNOWN
Platform: UNKNOWN
Classifier: Programming Language :: Python
Classifier: License :: OSI Approved :: MIT License
Classifier: Operating System :: OS Independent
